gigachat/__init__.py
gigachat/_types.py
gigachat/api/__init__.py
gigachat/api/assistants/__init__.py
gigachat/api/assistants/get_assistants.py
gigachat/api/assistants/post_assistant_delete.py
gigachat/api/assistants/post_assistant_files_delete.py
gigachat/api/assistants/post_assistant_modify.py
gigachat/api/assistants/post_assistants.py
gigachat/api/get_balance.py
gigachat/api/get_file.py
gigachat/api/get_files.py
gigachat/api/get_image.py
gigachat/api/get_model.py
gigachat/api/get_models.py
gigachat/api/post_ai_check.py
gigachat/api/post_auth.py
gigachat/api/post_chat.py
gigachat/api/post_embeddings.py
gigachat/api/post_files.py
gigachat/api/post_files_delete.py
gigachat/api/post_functions_convert.py
gigachat/api/post_token.py
gigachat/api/post_tokens_count.py
gigachat/api/stream_chat.py
gigachat/api/threads/__init__.py
gigachat/api/threads/get_threads.py
gigachat/api/threads/get_threads_messages.py
gigachat/api/threads/get_threads_run.py
gigachat/api/threads/post_thread_messages_rerun.py
gigachat/api/threads/post_thread_messages_rerun_stream.py
gigachat/api/threads/post_thread_messages_run.py
gigachat/api/threads/post_thread_messages_run_stream.py
gigachat/api/threads/post_threads_delete.py
gigachat/api/threads/post_threads_messages.py
gigachat/api/threads/post_threads_retrieve.py
gigachat/api/threads/post_threads_run.py
gigachat/api/utils.py
gigachat/assistants.py
gigachat/client.py
gigachat/context.py
gigachat/exceptions.py
gigachat/models/__init__.py
gigachat/models/access_token.py
gigachat/models/ai_check_result.py
gigachat/models/assistants/__init__.py
gigachat/models/assistants/assistant.py
gigachat/models/assistants/assistant_attachment.py
gigachat/models/assistants/assistant_delete.py
gigachat/models/assistants/assistant_file_delete.py
gigachat/models/assistants/assistants.py
gigachat/models/assistants/create_assistant.py
gigachat/models/balance.py
gigachat/models/chat.py
gigachat/models/chat_completion.py
gigachat/models/chat_completion_chunk.py
gigachat-0.1.42.post1.dist-info/LICENSE
gigachat-0.1.42.post1.dist-info/METADATA
gigachat-0.1.42.post1.dist-info/WHEEL
gigachat-0.1.42.post1.dist-info/RECORD
