Metadata-Version: 2.1
Name: gigachat
Version: 0.1.42.post1
Summary: GigaChat. Python-library for GigaChain and LangChain
Home-page: https://github.com/ai-forever/gigachat
License: MIT
Author: Konstantin Krestnikov
Author-email: rai220@gmail.com
Requires-Python: >=3.8,<4.0
Classifier: License :: OSI Approved :: MIT License
Classifier: Programming Language :: Python :: 3
Classifier: Programming Language :: Python :: 3.8
Classifier: Programming Language :: Python :: 3.9
Classifier: Programming Language :: Python :: 3.10
Classifier: Programming Language :: Python :: 3.11
Classifier: Programming Language :: Python :: 3.12
Requires-Dist: httpx (<1)
Requires-Dist: pydantic (>=1)
Project-URL: Repository, https://github.com/ai-forever/gigachat
